analitico/__init__.py
analitico/constants.py
analitico/dataset.py
analitico/exceptions.py
analitico/factory.py
analitico/item.py
analitico/logging.py
analitico/metadata.py
analitico/pandas.py
analitico/schema.py
analitico/sdk.py
analitico/status.py
analitico/utilities.py
analitico/mixin/__init__.py
analitico/mixin/attributemixin.py
analitico/models/__init__.py
analitico/models/dataset.py
analitico/models/item.py
analitico/models/notebook.py
analitico/models/recipe.py
analitico/models/workspace.py
analitico/plugin/__init__.py
analitico/plugin/augmentdatesplugin.py
analitico/plugin/catboostplugin.py
analitico/plugin/csvdataframesourceplugin.py
analitico/plugin/dataframepipelineplugin.py
analitico/plugin/datasetsourceplugin.py
analitico/plugin/endpointpipelineplugin.py
analitico/plugin/fusiondataframeplugin.py
analitico/plugin/interfaces.py
analitico/plugin/pipelineplugin.py
analitico/plugin/recipepipelineplugin.py
analitico/plugin/transformdataframeplugin.py
analitico/plugin/transforms.py
analitico/test/__init__.py
analitico/test/test_attributemixin.py
analitico/test/test_catboost.py
analitico/test/test_dataset.py
analitico/test/test_exception.py
analitico/test/test_factory.py
analitico/test/test_metadata.py
analitico/test/test_mixin.py
analitico/test/test_pandas.py
analitico/test/test_plugin.py
analitico/test/test_sdk.py
analitico/test/test_utilities.py
analitico/test/assets/ds_test_1.csv
analitico/test/assets/ds_test_1.json
analitico/test/assets/ds_test_2.csv
analitico/test/assets/ds_test_2.json
analitico/test/assets/ds_test_3.csv
analitico/test/assets/ds_test_3_cast_float.json
analitico/test/assets/ds_test_3_cast_string.json
analitico/test/assets/ds_test_4.csv
analitico/test/assets/ds_test_4.json
analitico/test/assets/ds_test_5_category.csv
analitico/test/assets/ds_test_5_category_no_schema.json
analitico/test/assets/ds_test_5_category_with_index.json
analitico/test/assets/ds_test_5_category_with_schema.json
analitico/test/assets/ds_test_6_weird_index.csv
analitico-2019.8.12.dev6.dist-info/LICENSE
analitico-2019.8.12.dev6.dist-info/METADATA
analitico-2019.8.12.dev6.dist-info/WHEEL
analitico-2019.8.12.dev6.dist-info/top_level.txt
analitico-2019.8.12.dev6.dist-info/RECORD
