Metadata-Version: 2.1
Name: analitico
Version: 2019.8.12.dev6
Summary: Python client for Analitico.ai
Home-page: https://github.com/analitico/analitico-sdk
Author: Analitico Labs, Inc.
Author-email: info@analitico.ai
License: UNKNOWN
Platform: UNKNOWN
Classifier: Development Status :: 2 - Pre-Alpha
Classifier: Environment :: Console
Classifier: Intended Audience :: Science/Research
Classifier: Intended Audience :: Developers
Classifier: Intended Audience :: Financial and Insurance Industry
Classifier: Intended Audience :: Information Technology
Classifier: License :: OSI Approved :: MIT License
Classifier: Operating System :: OS Independent
Classifier: Programming Language :: Python :: 3
Classifier: Programming Language :: Python :: 3.5
Classifier: Programming Language :: Python :: 3.6
Classifier: Programming Language :: Python :: 3.7
Classifier: Topic :: Scientific/Engineering :: Artificial Intelligence
Classifier: Topic :: Scientific/Engineering :: Information Analysis
Requires-Dist: catboost (>=0.11.1)
Requires-Dist: numpy (>=1.17.0)
Requires-Dist: pandas (>=0.24.0)
Requires-Dist: psutil (>=5.6.3)
Requires-Dist: simplejson (>=3.16.0)
Requires-Dist: pyarrow (>=0.14.1)
Requires-Dist: scikit-learn (>=0.21.3)
Requires-Dist: requests (>=2.21.0)
